[
  {
    "id": "LunYue-001",
    "sentence": "不仁者，不可以久處{{約}}。",
    "target": "約",
    "meaning": "窮困、貧困",
    "acptAns": ["窮困", "貧困", "困境", "困窘", "艱困", "匱乏"]
  },
  {
    "id": "LunYue-002",
    "sentence": "不可以長處{{樂}}。",
    "target": "樂",
    "meaning": "安樂、享樂",
    "acptAns": ["安樂", "享樂", "富足安樂", "順境", "快樂境地"]
  },
  {
    "id": "LunYue-003",
    "sentence": "仁者{{安}}仁。",
    "target": "安",
    "meaning": "安於、樂於、實行",
    "acptAns": ["安於", "樂於", "心安理得地", "安然處之", "自覺踐行"],
    "notes": "意動用法，指內心對行仁感到安適自然。"
  },
  {
    "id": "LunYue-004",
    "sentence": "{{知}}者利仁。",
    "target": "知",
    "meaning": "智慧、有智者",
    "acptAns": ["智慧", "智者", "聰明", "明理的人", "聰慧之士"],
    "notes": "通「智」，讀 zhì。"
  },
  {
    "id": "LunYue-005",
    "sentence": "知者{{利}}仁。",
    "target": "利",
    "meaning": "利用、藉著……得益",
    "acptAns": ["利用", "藉以得益", "趨利", "明白利害而行之", "因之獲益"]
  },
  {
    "id": "LunYue-006",
    "sentence": "富與貴，是人之所{{欲}}也。",
    "target": "欲",
    "meaning": "想要、渴求",
    "acptAns": ["想要", "渴求", "欲望", "期盼", "嚮往"]
  },
  {
    "id": "LunYue-007",
    "sentence": "不以其{{道}}得之，不處也。",
    "target": "道",
    "meaning": "正當的方法、正道",
    "acptAns": ["正當方法", "正道", "正途", "合理途徑", "道德準則"]
  },
  {
    "id": "LunYue-008",
    "sentence": "不以其道得之，不{{處}}也。",
    "target": "處",
    "meaning": "接受、享有、居處",
    "acptAns": ["接受", "享有", "安處", "佔有", "處於"]
  },
  {
    "id": "LunYue-009",
    "sentence": "貧與賤，是人之所{{惡}}也。",
    "target": "惡",
    "meaning": "厭惡、討厭",
    "acptAns": ["厭惡", "討厭", "憎惡", "不喜", "反感"],
    "notes": "讀 wù，動詞，非「邪惡」義。"
  },
  {
    "id": "LunYue-010",
    "sentence": "不以其道得之，不{{去}}也。",
    "target": "去",
    "meaning": "擺脫、離棄",
    "acptAns": ["擺脫", "離棄", "捨棄", "逃避", "除去"]
  },
  {
    "id": "LunYue-011",
    "sentence": "君子{{去}}仁，惡乎成名？",
    "target": "去",
    "meaning": "拋棄、捨棄",
    "acptAns": ["拋棄", "捨棄", "離開", "背離", "放棄"]
  },
  {
    "id": "LunYue-012",
    "sentence": "君子去仁，{{惡}}乎成名？",
    "target": "惡",
    "meaning": "哪裏、怎麼、如何",
    "acptAns": ["哪裏", "怎麼", "如何", "怎能", "何處"],
    "notes": "讀 wū，疑問代詞，非「邪惡」義。"
  },
  {
    "id": "LunYue-013",
    "sentence": "君子無{{終食之間}}違仁。",
    "target": "終食之間",
    "meaning": "一頓飯的時間、極短時間",
    "acptAns": ["一頓飯的時間", "吃一頓飯的功夫", "極短暫的時間", "片刻", "瞬間"]
  },
  {
    "id": "LunYue-014",
    "sentence": "君子無終食之間{{違}}仁。",
    "target": "違",
    "meaning": "違背、離開",
    "acptAns": ["違背", "離開", "背離", "偏離", "脫離"]
  },
  {
    "id": "LunYue-015",
    "sentence": "{{造次}}必於是。",
    "target": "造次",
    "meaning": "倉卒、匆忙的時候",
    "acptAns": ["倉卒", "匆忙", "匆促", "急遽", "慌亂之際"]
  },
  {
    "id": "LunYue-016",
    "sentence": "造次必{{於是}}。",
    "target": "於是",
    "meaning": "在此（指在仁德上）",
    "acptAns": ["在此", "在這裏", "對仁德", "堅守仁德", "於此"],
    "notes": "古漢語「於是」多作「在這裏/對此」解，非現代表因果用法。"
  },
  {
    "id": "LunYue-017",
    "sentence": "{{顛沛}}必於是。",
    "target": "顛沛",
    "meaning": "流離失所、困頓挫折",
    "acptAns": ["流離失所", "困頓", "挫折", "危難之際", "動盪困厄"]
  },
  {
    "id": "LunYue-018",
    "sentence": "{{克}}己復禮為仁。",
    "target": "克",
    "meaning": "克制、約束",
    "acptAns": ["克制", "約束", "抑制", "戰勝", "克服"]
  },
  {
    "id": "LunYue-019",
    "sentence": "克己{{復}}禮為仁。",
    "target": "復",
    "meaning": "回復、回歸、實踐",
    "acptAns": ["回復", "回歸", "踐行", "使恢復", "回到"]
  },
  {
    "id": "LunYue-020",
    "sentence": "一日克己復禮，天下{{歸}}仁焉。",
    "target": "歸",
    "meaning": "稱讚、推崇、歸向",
    "acptAns": ["稱讚", "讚許", "歸向", "稱許", "歸服"],
    "notes": "此處偏向「稱許、讚美」，非單指地理歸附。"
  },
  {
    "id": "LunYue-021",
    "sentence": "為仁{{由}}己，而由人乎哉？",
    "target": "由",
    "meaning": "依靠、取決於",
    "acptAns": ["依靠", "取決於", "在於", "憑藉", "源於"]
  },
  {
    "id": "LunYue-022",
    "sentence": "請問其{{目}}。",
    "target": "目",
    "meaning": "條目、細則",
    "acptAns": ["條目", "細則", "具體內容", "綱目", "細節"]
  },
  {
    "id": "LunYue-023",
    "sentence": "非禮勿{{視}}。",
    "target": "視",
    "meaning": "看",
    "acptAns": ["看", "觀看", "注視", "目視", "凝視"]
  },
  {
    "id": "LunYue-024",
    "sentence": "回雖不{{敏}}。",
    "target": "敏",
    "meaning": "聰敏、聰慧",
    "acptAns": ["聰敏", "聰明", "機敏", "聰穎", "資質聰慧"]
  },
  {
    "id": "LunYue-025",
    "sentence": "請{{事}}斯語矣。",
    "target": "事",
    "meaning": "實行、從事",
    "acptAns": ["實行", "從事", "實踐", "奉行", "照辦"]
  },
  {
    "id": "LunYue-026",
    "sentence": "請事{{斯}}語矣。",
    "target": "斯",
    "meaning": "這、這些",
    "acptAns": ["這", "這些", "此", "這樣", "這些話"]
  },
  {
    "id": "LunYue-027",
    "sentence": "志士仁人，無{{求生}}以害仁。",
    "target": "求生",
    "meaning": "貪生、苟且偷生",
    "acptAns": ["貪生", "苟且偷生", "為保命", "貪生怕死", "苟活"]
  },
  {
    "id": "LunYue-028",
    "sentence": "無求生以{{害}}仁。",
    "target": "害",
    "meaning": "損害、傷害",
    "acptAns": ["損害", "傷害", "破壞", "虧損", "妨害"]
  },
  {
    "id": "LunYue-029",
    "sentence": "有{{殺身}}以成仁。",
    "target": "殺身",
    "meaning": "犧牲生命",
    "acptAns": ["犧牲生命", "捨棄性命", "捐軀", "犧牲自己", "獻出生命"]
  },
  {
    "id": "LunYue-030",
    "sentence": "孟懿子問孝。子曰：「{{無違}}。」",
    "target": "無違",
    "meaning": "不要違背（禮節）",
    "acptAns": ["不要違背", "不違逆", "不違背禮節", "順從", "勿違禮"],
    "notes": "專指不違背「禮」的規範，非泛指聽話。"
  },
  {
    "id": "LunYue-031",
    "sentence": "樊遲{{御}}。",
    "target": "御",
    "meaning": "駕車、趕馬車",
    "acptAns": ["駕車", "趕馬車", "駕駛", "為……駕車", "執鞭駕車"]
  },
  {
    "id": "LunYue-032",
    "sentence": "孟孫問孝{{於}}我。",
    "target": "於",
    "meaning": "向",
    "acptAns": ["向", "對", "跟", "向（某人）請教", "詢問"]
  },
  {
    "id": "LunYue-033",
    "sentence": "我{{對}}曰，無違。",
    "target": "對",
    "meaning": "回答",
    "acptAns": ["回答", "答道", "回應", "回覆", "答覆"]
  },
  {
    "id": "LunYue-034",
    "sentence": "樊遲曰：「{{何謂}}也？」",
    "target": "何謂",
    "meaning": "什麼意思、指什麼",
    "acptAns": ["什麼意思", "指什麼", "是什麼意思", "怎麼講", "何所指"]
  },
  {
    "id": "LunYue-035",
    "sentence": "{{生}}事之以禮。",
    "target": "生",
    "meaning": "生前、父母在世時",
    "acptAns": ["生前", "父母在世時", "活著的時候", "健在時", "在世"]
  },
  {
    "id": "LunYue-036",
    "sentence": "生{{事}}之以禮。",
    "target": "事",
    "meaning": "侍奉",
    "acptAns": ["侍奉", "服侍", "照顧", "孝敬", "奉養"]
  },
  {
    "id": "LunYue-037",
    "sentence": "死{{葬}}之以禮。",
    "target": "葬",
    "meaning": "安葬、埋葬",
    "acptAns": ["安葬", "埋葬", "下葬", "殯葬", "處理喪事"]
  },
  {
    "id": "LunYue-038",
    "sentence": "今之孝者，是{{謂}}能養。",
    "target": "謂",
    "meaning": "說、認為",
    "acptAns": ["說", "認為", "稱作", "以為", "說成"]
  },
  {
    "id": "LunYue-039",
    "sentence": "今之孝者，是謂能{{養}}。",
    "target": "養",
    "meaning": "供養、奉養（只給予物質）",
    "acptAns": ["供養", "奉養", "養活", "供給食物", "物質奉養"],
    "notes": "側重物質層面，與下句「敬」形成對比。"
  },
  {
    "id": "LunYue-040",
    "sentence": "至於犬馬，皆能有{{養}}。",
    "target": "養",
    "meaning": "得到飼養",
    "acptAns": ["得到飼養", "受養", "被飼養", "受餵養", "得到照料"],
    "notes": "被動用法，指動物亦能獲得物質照顧。"
  },
  {
    "id": "LunYue-041",
    "sentence": "不{{敬}}，何以別乎？",
    "target": "敬",
    "meaning": "尊敬、恭敬",
    "acptAns": ["尊敬", "恭敬", "敬重", "尊重", "誠敬"]
  },
  {
    "id": "LunYue-042",
    "sentence": "不敬，{{何以}}別乎？",
    "target": "何以",
    "meaning": "憑什麼、怎麼",
    "acptAns": ["憑什麼", "怎麼", "如何", "怎樣", "用什麼"]
  },
  {
    "id": "LunYue-043",
    "sentence": "事父母{{幾}}諫。",
    "target": "幾",
    "meaning": "輕微、婉轉",
    "acptAns": ["輕微", "婉轉", "委婉", "含蓄", "適度"],
    "notes": "讀 jī，指勸諫時態度溫和、措辭委婉。"
  },
  {
    "id": "LunYue-044",
    "sentence": "事父母幾{{諫}}。",
    "target": "諫",
    "meaning": "勸諫、規勸",
    "acptAns": ["勸諫", "規勸", "勸告", "直言勸阻", "勸導"]
  },
  {
    "id": "LunYue-045",
    "sentence": "見{{志}}不從，又敬不違。",
    "target": "志",
    "meaning": "心意",
    "acptAns": ["心意", "意見", "想法", "意願", "主張"]
  },
  {
    "id": "LunYue-046",
    "sentence": "見志不{{從}}，又敬不違。",
    "target": "從",
    "meaning": "聽從、採納",
    "acptAns": ["聽從", "採納", "接受", "順從", "聽取"]
  },
  {
    "id": "LunYue-047",
    "sentence": "見志不從，又敬不{{違}}。",
    "target": "違",
    "meaning": "違逆、冒犯",
    "acptAns": ["違逆", "冒犯", "頂撞", "觸犯", "不順從"]
  },
  {
    "id": "LunYue-048",
    "sentence": "{{勞}}而不怨。",
    "target": "勞",
    "meaning": "勞苦、擔憂",
    "acptAns": ["勞苦", "擔憂", "操心", "辛苦", "憂慮"]
  },
  {
    "id": "LunYue-049",
    "sentence": "父母之年，不可不{{知}}也。",
    "target": "知",
    "meaning": "知道、記得",
    "acptAns": ["知道", "記得", "留意", "記掛", "清楚"]
  },
  {
    "id": "LunYue-050",
    "sentence": "一則以喜，一則以{{懼}}。",
    "target": "懼",
    "meaning": "擔憂、恐懼",
    "acptAns": ["擔憂", "恐懼", "害怕", "憂慮", "擔心"]
  },
  {
    "id": "LunYue-051",
    "sentence": "君子不{{重}}則不威。",
    "target": "重",
    "meaning": "莊重、穩重",
    "acptAns": ["莊重", "穩重", "持重", "端莊", "慎重"]
  },
  {
    "id": "LunYue-052",
    "sentence": "君子不重則不{{威}}。",
    "target": "威",
    "meaning": "威嚴、威信",
    "acptAns": ["威嚴", "威信", "威望", "威儀", "令人敬畏"]
  },
  {
    "id": "LunYue-053",
    "sentence": "學則不{{固}}。",
    "target": "固",
    "meaning": "固陋、蔽塞",
    "acptAns": ["固陋", "蔽塞", "頑固", "偏執", "見識淺陋"],
    "notes": "HKDSE 主流取「固陋/蔽塞」義；另一說為「堅固」，但評卷多取前者。"
  },
  {
    "id": "LunYue-054",
    "sentence": "{{主}}忠信。",
    "target": "主",
    "meaning": "注重、推崇",
    "acptAns": ["注重", "推崇", "重視", "以……為主", "秉持"]
  },
  {
    "id": "LunYue-055",
    "sentence": "無友{{不如}}己者。",
    "target": "不如",
    "meaning": "不及、不像",
    "acptAns": ["不及", "比不上", "不如自己", "不及自己", "比不上自己"],
    "notes": "歷代有爭議，HKDSE 標準答案為「不及/比不上自己」。"
  },
  {
    "id": "LunYue-056",
    "sentence": "{{過}}則勿憚改。",
    "target": "過",
    "meaning": "過錯、犯錯",
    "acptAns": ["過錯", "犯錯", "錯誤", "失誤", "過失"]
  },
  {
    "id": "LunYue-057",
    "sentence": "過則勿{{憚}}改。",
    "target": "憚",
    "meaning": "害怕、畏懼",
    "acptAns": ["害怕", "畏懼", "恐懼", "忌憚", "擔心"]
  },
  {
    "id": "LunYue-058",
    "sentence": "君子{{坦蕩蕩}}。",
    "target": "坦蕩蕩",
    "meaning": "胸懷寬廣、心胸開闊",
    "acptAns": ["胸懷寬廣", "心胸開闊", "光明磊落", "坦率無私", "開闊明朗"]
  },
  {
    "id": "LunYue-059",
    "sentence": "小人{{長戚戚}}。",
    "target": "長戚戚",
    "meaning": "經常憂愁、憂心忡忡",
    "acptAns": ["經常憂愁", "憂心忡忡", "患得患失", "斤斤計較", "憂慮不安"]
  },
  {
    "id": "LunYue-060",
    "sentence": "君子不{{憂}}不懼。",
    "target": "憂",
    "meaning": "憂慮",
    "acptAns": ["憂慮", "擔心", "煩惱", "憂愁", "畏懼"]
  },
  {
    "id": "LunYue-061",
    "sentence": "{{斯}}謂之君子矣乎？",
    "target": "斯",
    "meaning": "這、這樣",
    "acptAns": ["這", "這樣", "此", "如此", "這樣的人"]
  },
  {
    "id": "LunYue-062",
    "sentence": "斯謂之君子{{已}}乎？",
    "target": "已",
    "meaning": "罷了",
    "acptAns": ["罷了", "而已", "為止", "就算了", "就算完了"],
    "notes": "語氣助詞，表限制或輕微反問。"
  },
  {
    "id": "LunYue-063",
    "sentence": "{{內省}}不疚。",
    "target": "內省",
    "meaning": "自我反省",
    "acptAns": ["自我反省", "反省自己", "檢討內心", "自我檢視", "內察"]
  },
  {
    "id": "LunYue-064",
    "sentence": "內省不{{疚}}。",
    "target": "疚",
    "meaning": "愧疚、慚愧",
    "acptAns": ["愧疚", "慚愧", "內疚", "歉疚", "不安"]
  },
  {
    "id": "LunYue-065",
    "sentence": "夫何憂{{何}}懼？",
    "target": "何",
    "meaning": "什麼",
    "acptAns": ["什麼", "哪有", "何必", "哪裏", "怎麼"]
  },
  {
    "id": "LunYue-066",
    "sentence": "君子{{成人之美}}。",
    "target": "成人之美",
    "meaning": "成全別人的好事",
    "acptAns": ["成全別人的好事", "幫助他人成功", "促成他人善舉", "樂見他人得益", "助人達願"]
  },
  {
    "id": "LunYue-067",
    "sentence": "不{{成人之惡}}。",
    "target": "成人之惡",
    "meaning": "助長別人的壞事",
    "acptAns": ["助長別人的壞事", "促成他人惡行", "幫助別人做壞事", "助紂為虐", "縱容惡行"]
  },
  {
    "id": "LunYue-068",
    "sentence": "小人{{反}}是。",
    "target": "反",
    "meaning": "相反",
    "acptAns": ["相反", "背道而馳", "截然不同", "違反", "顛倒"]
  },
  {
    "id": "LunYue-069",
    "sentence": "小人反{{是}}。",
    "target": "是",
    "meaning": "這（指君子的做法）",
    "acptAns": ["這", "這樣", "此種做法", "君子所為", "上述原則"]
  },
  {
    "id": "LunYue-070",
    "sentence": "君子{{恥}}其言而過其行。",
    "target": "恥",
    "meaning": "以……為恥、感到羞恥",
    "acptAns": ["以……為恥", "感到羞恥", "覺得可恥", "引以為恥", "羞於"],
    "notes": "意動用法。"
  },
  {
    "id": "LunYue-071",
    "sentence": "君子恥其言而{{過}}其行。",
    "target": "過",
    "meaning": "超過、勝過",
    "acptAns": ["超過", "勝過", "多於", "超越", "實際做到超過"]
  },
  {
    "id": "LunYue-072",
    "sentence": "君子{{義}}以為質。",
    "target": "義",
    "meaning": "道義、正義",
    "acptAns": ["道義", "正義", "宜", "合理準則", "道德原則"]
  },
  {
    "id": "LunYue-073",
    "sentence": "君子義以為{{質}}。",
    "target": "質",
    "meaning": "本質、原則、根本",
    "acptAns": ["本質", "原則", "根本", "根基", "內在核心"]
  },
  {
    "id": "LunYue-074",
    "sentence": "禮以{{行}}之。",
    "target": "行",
    "meaning": "實行、推行",
    "acptAns": ["實行", "推行", "實踐", "履行", "執行"]
  },
  {
    "id": "LunYue-075",
    "sentence": "{{孫}}以出之。",
    "target": "孫",
    "meaning": "謙遜、謙虛",
    "acptAns": ["謙遜", "謙虛", "遜讓", "謙恭", "低調"],
    "notes": "通「遜」。"
  },
  {
    "id": "LunYue-076",
    "sentence": "孫以{{出}}之。",
    "target": "出",
    "meaning": "說出、表達",
    "acptAns": ["說出", "表達", "表現", "流露", "言辭表達"]
  },
  {
    "id": "LunYue-077",
    "sentence": "信以{{成}}之。",
    "target": "成",
    "meaning": "完成、成就",
    "acptAns": ["完成", "成就", "達成", "實現", "圓滿"]
  },
  {
    "id": "LunYue-078",
    "sentence": "君子{{病}}無能焉。",
    "target": "病",
    "meaning": "擔憂、憂慮",
    "acptAns": ["擔憂", "憂慮", "憂心", "引以為憂", "苦惱"],
    "notes": "意動用法，指以自身能力不足為憂。"
  },
  {
    "id": "LunYue-079",
    "sentence": "不{{病}}人之不己知也。",
    "target": "病",
    "meaning": "擔憂",
    "acptAns": ["擔憂", "憂慮", "擔心", "介意", "苦惱"]
  },
  {
    "id": "LunYue-080",
    "sentence": "君子求{{諸}}己。",
    "target": "諸",
    "meaning": "之於",
    "acptAns": ["之於", "於之", "在這方面", "對它", "向自己"],
    "notes": "兼詞，「之」代指目標，「於」表對象。"
  },
  {
    "id": "LunYue-081",
    "sentence": "小人求諸{{人}}。",
    "target": "人",
    "meaning": "別人、他人",
    "acptAns": ["別人", "他人", "外人", "旁人", "他人幫助"]
  }
]
